{
    "id":"phillies",
    "name": "Philadelphia Phillies",
    "since": 1883,
    "hometown": [
        {"no": 1, "city": "Philadelphia"}
    ],
    "field": "Citizens Bank Park",
    "fieldImg": "citizensBankPark.jpg",
    "worldseries": [
        {"no": 1, "year": 1980},
        {"no": 2, "year": 2008}
    ],
    "logo": "phillies.svg",
    "keyword": "필라델피아인",
    "history": "긴 역사와 전통을 자랑하는 필라델피아 필리스는 현재는 아니지만 한때 메이저 리그를 대표하는 약팀 중 하나였으며 전 세계 프로 스포츠 역사상 최초의 10,000패를 달성했기 때문에 국내 팬들에게 만패라는 멸칭으로 불린다. 단지 구단 역사가 오래되어서 얻게 된 기록이 아닌 것이, 다른 후발 만패팀들의 경우 통산 승률 5할이 넘는 반면필리스는 혼자서 -1000이 넘는 놀라운 승패 마진을 자랑한다. 2022년 8월 16일에는 드디어 염원하던 10,000승을 기록하였다.",
    "permanentNumber": [
        {
            "no": 1,
            "teamColor": "#d63031",
            "pic": "richieAshburn.jpg",
            "name": "Richie Ashburn"
        },
        {
            "no": 14,
            "teamColor": "#d63031",
            "pic": "jimBunning.jpg",
            "name": "Jim Bunning"
        },
        {
            "no": 15,
            "teamColor": "#d63031",
            "pic": "dickAllen.jpg",
            "name": "Dick Allen"
        },
        {
            "no": 20,
            "teamColor": "#d63031",
            "pic": "mikeSchmidt.jpg",
            "name": "Mike Schmidt"
        },
        {
            "no": 32,
            "teamColor": "#d63031",
            "pic": "steveCarlton.webp",
            "name": "Steve Carlton"
        },
        {
            "no": 34,
            "teamColor": "#d63031",
            "pic": "royHalladay.webp",
            "name": "Roy Halladay"
        },
        {
            "no": 36,
            "teamColor": "#d63031",
            "pic": "robinRoberts.webp",
            "name": "Robin Roberts"
        },
        {
            "no": 42,
            "teamColor": "#2980b9",
            "pic": "jackieRobinson.jpg",
            "name": "Jackie Robinson"
        }
    ]
}